<SOAP-ENV:Envelope xmlns:SOAP-ENV="http://schemas.xmlsoap.org/soap/envelope/" SOAP-ENV:encodingStyle="http://schemas.xmlsoap.org/soap/encoding/"><SOAP-ENV:Body><SOAPSDK1:echoSimpleTypesAsStructResponse xmlns:SOAPSDK1="http://soapinterop.org/"><return xmlns="" xmlns:si="http://soapinterop.org/xsd" xmlns:xsi="http://www.w3.org/2001/XMLSchema-instance" xmlns:xsd="http://www.w3.org/2001/XMLSchema" xsi:type="si:SOAPStruct"><varString xmlns="" xsi:type="xsd:string">45ascasc  acasa asd52</varString><varInt xmlns="" xsi:type="xsd:int">4552</varInt><varFloat xmlns="" xsi:type="xsd:float">450.519989013672</varFloat></return></SOAPSDK1:echoSimpleTypesAsStructResponse></SOAP-ENV:Body></SOAP-ENV:Envelope>