<SOAP-ENV:Envelope xmlns:xsi="http://www.w3.org/2001/XMLSchema-instance" xmlns:SOAP-ENV="http://schemas.xmlsoap.org/soap/envelope/" SOAP-ENV:encodingStyle="http://schemas.xmlsoap.org/soap/encoding/" xmlns:xsd="http://www.w3.org/2001/XMLSchema">
      <SOAP-ENV:Body>
         <ns1:echoStructArrayResponse xmlns:ns1="http://soapinterop.org/">
            <return xmlns:ns2="http://schemas.xmlsoap.org/soap/encoding/"  xsi:type="ns2:Array" xmlns:ns3="http://soapinterop.org/xsd"  ns2:arrayType="ns3:SOAPStruct[3]">
               <item xsi:type="ns3:SOAPStruct">
                  <varString xsi:type="xsd:string">strss fdfing1</varString>
                  <varInt xsi:type="xsd:int">25</varInt>
                  <varFloat xsi:type="xsd:float">25.23</varFloat>
               </item>
               <item xsi:type="ns3:SOAPStruct">
                  <varString xsi:type="xsd:string">strss fdfing1</varString>
                  <varInt xsi:type="xsd:int">25</varInt>
                  <varFloat xsi:type="xsd:float">25.23</varFloat>
               </item>
               <item xsi:type="ns3:SOAPStruct">
                  <varString xsi:type="xsd:string">strss fdfing1</varString>
                  <varInt xsi:type="xsd:int">25</varInt>
                  <varFloat xsi:type="xsd:float">25.23</varFloat>
               </item>
            </return>
         </ns1:echoStructArrayResponse>
      </SOAP-ENV:Body>
   </SOAP-ENV:Envelope>
